llama_index/vector_stores/azurecosmosnosql/__init__.py
llama_index/vector_stores/azurecosmosnosql/base.py
llama_index_vector_stores_azurecosmosnosql-1.4.1.dist-info/METADATA
llama_index_vector_stores_azurecosmosnosql-1.4.1.dist-info/WHEEL
llama_index_vector_stores_azurecosmosnosql-1.4.1.dist-info/licenses/LICENSE
llama_index_vector_stores_azurecosmosnosql-1.4.1.dist-info/RECORD
