Metadata-Version: 2.4
Name: llama-index-vector-stores-azurecosmosnosql
Version: 1.4.1
Summary: llama-index vector_stores azurecosmosnosql integration
Author-email: Aayush Kataria <aayushkataria3011@gmail.com>
License-Expression: MIT
License-File: LICENSE
Requires-Python: <4.0,>=3.9
Requires-Dist: azure-cosmos<5,>=4.9.0
Requires-Dist: azure-identity<2,>=1.19.0
Requires-Dist: llama-index-core<0.15,>=0.13.0
